atmn/ScenarioExporter.py
atmn/ScenarioGenerator.py
atmn/ScenarioLoader.py
atmn/ScenarioVisualizer.py
atmn/__init__.py
atmn/__main__.py
atmn/config_schema.xsd
atmn-1.1.0.dist-info/METADATA
atmn-1.1.0.dist-info/WHEEL
atmn-1.1.0.dist-info/entry_points.txt
atmn-1.1.0.dist-info/licenses/LICENSE
atmn-1.1.0.dist-info/RECORD
